[
    { "id": "0", "name": "UP9",                     "type": "weaponsecondary", "concealed": false, "offhand": false, "weight": 3, "space": 3, "cap": -1 },
    { "id": "1", "name": "K45",                     "type": "weaponsecondary", "concealed": false, "offhand": false, "weight": 3, "space": 3, "cap": -1 },
    { "id": "2", "name": "S97",                     "type": "weaponsecondary", "concealed": false, "offhand": false, "weight": 4, "space": 4, "cap": -1 },
    { "id": "3", "name": "480 MCS",                 "type": "weaponprimary", "concealed": false, "offhand": false, "weight": 7, "space": 7, "cap": -1 },
    { "id": "4", "name": "CBR-C",                   "type": "weaponprimary", "concealed": false, "offhand": false, "weight": 6, "space": 6, "cap": -1 },
    { "id": "5", "name": "F57",                     "type": "weaponprimary", "concealed": false, "offhand": false, "weight": 8, "space": 8, "cap": -1 },
    { "id": "6", "name": "The Lance",               "type": "weaponprimary", "concealed": false, "offhand": false, "weight": 6, "space": 5, "cap": -1 },
    
    { "id": "7", "name": "Drill",                   "type": "tools", "concealed": false, "offhand": false, "space": 4, "weight": 4, "cap": 1 },
    { "id": "8", "name": "Saw",                     "type": "tools", "concealed": false, "offhand": false, "space": 4, "weight": 4, "cap": 1 },
    { "id": "39", "name": "Blowtorch",              "type": "tools", "concealed": false, "offhand": false, "space": 2, "weight": 3, "cap": 1 },
    { "id": "9", "name": "Screwdriver",             "type": "tools", "concealed": false, "offhand": false, "space": 1, "weight": 0.6, "cap": 1 },
    { "id": "10", "name": "Lockpick Kit",           "type": "tools", "concealed": false, "offhand": false, "space": 2, "weight": 1, "cap": 1 },
    { "id": "11", "name": "Hacking Tablet",         "type": "tools", "concealed": false, "offhand": false, "space": 3, "weight": 4, "cap": 1 },
    { "id": "12", "name": "Pineapple",              "type": "tools", "concealed": false, "offhand": false, "space": 2, "weight": 3, "cap": 1 },
    { "id": "13", "name": "Rewire Kit",             "type": "tools", "concealed": false, "offhand": false, "space": 2, "weight": 1, "cap": 1 },
    { "id": "14", "name": "Trackers",               "type": "tools", "concealed": false, "offhand": false, "space": 1, "weight": 1, "cap": 1 },
    { "id": "40", "name": "Breaching Charge",       "type": "combat", "concealed": false, "offhand": false, "space": 2, "weight": 3, "cap": 1 },

    { "id": "15", "name": "C4",                     "type": "combat", "concealed": false, "offhand": false, "space": 3, "weight": 3, "cap": 1 },
    { "id": "16", "name": "Frag Grenades",          "type": "combat", "concealed": false, "offhand": false, "space": 3, "weight": 3, "cap": 1 },
    { "id": "17", "name": "Medkit",                 "type": "combat", "concealed": false, "offhand": false, "space": 3, "weight": 4, "cap": 1 },
    { "id": "18", "name": "Ammobox",                "type": "combat", "concealed": false, "offhand": true, "space": 6, "weight": 6, "cap": 1 },
    { "id": "19", "name": "Ballistic Shield",       "type": "combat", "concealed": false, "offhand": true, "space": -1, "weight": 9, "cap": 1 },

    { "id": "20", "name": "Ammo Pouches",           "type": "concealed", "concealed": true, "offhand": false, "space": 0, "weight": 0, "cap": 1 },
    { "id": "21", "name": "Concealed Pockets",      "type": "concealed", "concealed": true, "offhand": false, "space": 0, "weight": 0, "cap": 1 },
    { "id": "22", "name": "Custom Holsters",        "type": "concealed", "concealed": true, "offhand": false, "space": 0, "weight": 0, "cap": 1 },
    
    { "id": "23", "name": "Concealed Scout Armour", "type": "armour", "concealed": true, "offhand": false, "space": -1, "weight": 10, "cap": 1 },
    { "id": "24", "name": "Scout Armour",           "type": "armour", "concealed": false, "offhand": false, "space": 7, "weight": 10, "cap": 1 },
    { "id": "24", "name": "Frontline Armour",       "type": "armour", "concealed": false, "offhand": false, "space": 9, "weight": 16, "cap": 1 },

    { "id": "25", "name": "Budget Suppressor",      "type": "weaponmod", "concealed": false, "offhand": false, "space": 2, "weight": 0, "cap": 1 },
    { "id": "26", "name": "Lynx Suppressor",        "type": "weaponmod", "concealed": false, "offhand": false, "space": 2, "weight": 0, "cap": 1 },
    { "id": "27", "name": "Reservior Suppressor",   "type": "weaponmod", "concealed": false, "offhand": false, "space": 2, "weight": 0, "cap": 1 },
    { "id": "28", "name": "Lookout Suppressor",     "type": "weaponmod", "concealed": false, "offhand": false, "space": 3, "weight": 0, "cap": 1 },
    { "id": "29", "name": "Lance Suppressor",       "type": "weaponmod", "concealed": false, "offhand": false, "space": 3, "weight": 0, "cap": 1 },
    { "id": "30", "name": "Muzzle Brake",           "type": "weaponmod", "concealed": false, "offhand": false, "space": 1, "weight": 0, "cap": 1 },
    { "id": "31", "name": "Compensator",            "type": "weaponmod", "concealed": false, "offhand": false, "space": 1, "weight": 0, "cap": 1 },
    { "id": "32", "name": "Duckbill",               "type": "weaponmod", "concealed": false, "offhand": false, "space": 1, "weight": 0, "cap": 1 },
    { "id": "33", "name": "Choke",                  "type": "weaponmod", "concealed": false, "offhand": false, "space": 1, "weight": 0, "cap": 1 },
    { "id": "34", "name": "Mini Sight",             "type": "weaponmod", "concealed": false, "offhand": false, "space": 0, "weight": 0, "cap": 1 },
    { "id": "35", "name": "Red Dot Sight",          "type": "weaponmod", "concealed": false, "offhand": false, "space": 1, "weight": 0, "cap": 1 },
    { "id": "36", "name": "TG3X",                   "type": "weaponmod", "concealed": false, "offhand": false, "space": 2, "weight": 0, "cap": 1 },
    { "id": "37", "name": "Magnifier",              "type": "weaponmod", "concealed": false, "offhand": false, "space": 1, "weight": 0, "cap": 1 },
    { "id": "38", "name": "Laser",                  "type": "weaponmod", "concealed": false, "offhand": false, "space": 0, "weight": 0, "cap": 1 }
]